pykada/access_control.py
pykada/api_tokens.py
pykada/camera_stream.py
pykada/cameras.py
pykada/classic_alarms.py
pykada/core_command.py
pykada/endpoints.py
pykada/enums.py
pykada/helix.py
pykada/helpers.py
pykada/sensors.py
pykada/verkada_client.py
pykada/verkada_requests.py
pykada/workplace.py
pykada/access_control_tests/test_access_control.py
pykada/access_control_tests/test_access_control_credentials.py
pykada/access_control_tests/test_access_doors.py
pykada/access_control_tests/test_access_events.py
pykada/access_control_tests/test_access_groups.py
pykada/access_control_tests/test_access_levels.py
pykada/access_control_tests/test_access_users.py
pykada/access_control_tests/test_door_exceptions.py
pykada/access_control_tests/testbed/Cary-Grant.png
pykada/access_control_tests/testbed/testbed.py
pykada/cameras_tests/test_cameras.py
pykada/cameras_tests/testbed/Cary-Grant.png
pykada/cameras_tests/testbed/delete_licenseplates.csv
pykada/cameras_tests/testbed/licenseplates.csv
pykada/cameras_tests/testbed/testbed.py
pykada/cameras_tests/testbed/testbed_oop.py
pykada/classic_alarms/test_classic_alarms.py
pykada/classic_alarms/testbed/testbed.py
pykada/core_command/test_core_command.py
pykada/core_command/testbed/testbed.py
pykada/helix/test_helix.py
pykada/helix/testbed/testbed.py
pykada/sensors/test_sensor.py
pykada/sensors/testbed/testbed.py
pykada/workplace/deny_list_example.csv
pykada/workplace/test_workplace.py
pykada/workplace/testbed/testbed.py
pykada-1.0.3.dist-info/METADATA
pykada-1.0.3.dist-info/WHEEL
pykada-1.0.3.dist-info/RECORD
