Metadata-Version: 2.4
Name: pykada
Version: 1.0.3
Summary: A handy library for interacting with Verkada APIs.
Project-URL: Homepage, https://github.com/ryanmalley101/pykada
Project-URL: Issues, https://github.com/ryanmalley101/pykada/issues
Author-email: Ryan Malley <ryanmalley101@gmail.com>
Classifier: Operating System :: OS Independent
Classifier: Programming Language :: Python :: 3
Requires-Python: >=3.10
Requires-Dist: numpy~=2.2.6
Requires-Dist: pandas~=2.3.2
Requires-Dist: pytest~=8.4.1
Requires-Dist: python-dotenv~=1.1.0
Requires-Dist: python-vlc~=3.0.21203
Requires-Dist: requests~=2.32.3
Requires-Dist: termcolor~=3.1.0
Requires-Dist: typeguard~=4.4.2
Requires-Dist: urllib3~=2.5.0
